README.md
setup.py
koradctl/__init__.py
koradctl/__main__.py
koradctl/args.py
koradctl/cli.py
koradctl/package.py
koradctl/port.py
koradctl/pretty.py
koradctl/psu.py
koradctl/test.py
koradctl/types.py
koradctl.egg-info/PKG-INFO
koradctl.egg-info/SOURCES.txt
koradctl.egg-info/dependency_links.txt
koradctl.egg-info/entry_points.txt
koradctl.egg-info/requires.txt
koradctl.egg-info/top_level.txt